motopy/__init__.py
motopy/constants.py
motopy/generate.py
motopy/parse.py
motopy/port.py
motopy/scan.py
motopy/token.py
motopy/translate.py
motopy/utils.py
motopy-2.1.0.dist-info/METADATA
motopy-2.1.0.dist-info/WHEEL
motopy-2.1.0.dist-info/licenses/LICENSE
motopy-2.1.0.dist-info/RECORD
