Metadata-Version: 2.1
Name: motopy
Version: 2.1.0
Summary: The tool of converting Matlab/Octave code TO PYthon.
Project-URL: Homepage, https://github.com/falwat/motopy
Project-URL: Bug Tracker, https://github.com/falwat/motopy/issues
Author-email: Jackie Wang <falwat@163.com>
License-Expression: MIT
License-File: LICENSE
Classifier: License :: OSI Approved :: MIT License
Classifier: Operating System :: OS Independent
Classifier: Programming Language :: Python :: 3
Requires-Python: >=3.7
